{
  "matchId": "18188721",
  "homeTeam": "Paraguay",
  "awayTeam": "France",
  "finalScore": {
    "home": 0,
    "away": 1
  },
  "stats": [
    {
      "key": "shots",
      "label": "Shots",
      "home": 4,
      "away": 19,
      "kind": "derived",
      "events": 23
    },
    {
      "key": "shotsOnTarget",
      "label": "Shots on target",
      "home": 1,
      "away": 6,
      "kind": "derived",
      "events": 7
    },
    {
      "key": "possession",
      "label": "Possession",
      "home": 37,
      "away": 63,
      "unit": "%",
      "kind": "derived",
      "events": 723
    },
    {
      "key": "corners",
      "label": "Corners",
      "home": 2,
      "away": 12,
      "kind": "verified",
      "proofHome": {
        "fixtureId": 18188721,
        "seq": 965,
        "statKey": 7,
        "timestamp": 1783207388027,
        "epochDay": 20638,
        "rootPda": "DjE6qSDHJEUwbXXTV5v1YSQpzfsWcRsARbWqLqR3KoSA",
        "explorerUrl": "https://explorer.solana.com/address/DjE6qSDHJEUwbXXTV5v1YSQpzfsWcRsARbWqLqR3KoSA?cluster=devnet",
        "statValidationUrl": "https://txline-dev.txodds.com/api/scores/stat-validation?fixtureId=18188721&seq=965&statKey=7"
      },
      "proofAway": {
        "fixtureId": 18188721,
        "seq": 965,
        "statKey": 8,
        "timestamp": 1783207388027,
        "epochDay": 20638,
        "rootPda": "DjE6qSDHJEUwbXXTV5v1YSQpzfsWcRsARbWqLqR3KoSA",
        "explorerUrl": "https://explorer.solana.com/address/DjE6qSDHJEUwbXXTV5v1YSQpzfsWcRsARbWqLqR3KoSA?cluster=devnet",
        "statValidationUrl": "https://txline-dev.txodds.com/api/scores/stat-validation?fixtureId=18188721&seq=965&statKey=8"
      }
    },
    {
      "key": "yellow",
      "label": "Yellow cards",
      "home": 0,
      "away": 3,
      "kind": "verified",
      "proofHome": {
        "fixtureId": 18188721,
        "seq": 965,
        "statKey": 3,
        "timestamp": 1783207388027,
        "epochDay": 20638,
        "rootPda": "DjE6qSDHJEUwbXXTV5v1YSQpzfsWcRsARbWqLqR3KoSA",
        "explorerUrl": "https://explorer.solana.com/address/DjE6qSDHJEUwbXXTV5v1YSQpzfsWcRsARbWqLqR3KoSA?cluster=devnet",
        "statValidationUrl": "https://txline-dev.txodds.com/api/scores/stat-validation?fixtureId=18188721&seq=965&statKey=3"
      },
      "proofAway": {
        "fixtureId": 18188721,
        "seq": 965,
        "statKey": 4,
        "timestamp": 1783207388027,
        "epochDay": 20638,
        "rootPda": "DjE6qSDHJEUwbXXTV5v1YSQpzfsWcRsARbWqLqR3KoSA",
        "explorerUrl": "https://explorer.solana.com/address/DjE6qSDHJEUwbXXTV5v1YSQpzfsWcRsARbWqLqR3KoSA?cluster=devnet",
        "statValidationUrl": "https://txline-dev.txodds.com/api/scores/stat-validation?fixtureId=18188721&seq=965&statKey=4"
      }
    },
    {
      "key": "red",
      "label": "Red cards",
      "home": 0,
      "away": 0,
      "kind": "verified",
      "proofHome": {
        "fixtureId": 18188721,
        "seq": 965,
        "statKey": 5,
        "timestamp": 1783207388027,
        "epochDay": 20638,
        "rootPda": "DjE6qSDHJEUwbXXTV5v1YSQpzfsWcRsARbWqLqR3KoSA",
        "explorerUrl": "https://explorer.solana.com/address/DjE6qSDHJEUwbXXTV5v1YSQpzfsWcRsARbWqLqR3KoSA?cluster=devnet",
        "statValidationUrl": "https://txline-dev.txodds.com/api/scores/stat-validation?fixtureId=18188721&seq=965&statKey=5"
      },
      "proofAway": {
        "fixtureId": 18188721,
        "seq": 965,
        "statKey": 6,
        "timestamp": 1783207388027,
        "epochDay": 20638,
        "rootPda": "DjE6qSDHJEUwbXXTV5v1YSQpzfsWcRsARbWqLqR3KoSA",
        "explorerUrl": "https://explorer.solana.com/address/DjE6qSDHJEUwbXXTV5v1YSQpzfsWcRsARbWqLqR3KoSA?cluster=devnet",
        "statValidationUrl": "https://txline-dev.txodds.com/api/scores/stat-validation?fixtureId=18188721&seq=965&statKey=6"
      }
    }
  ],
  "source": "TxLINE on-chain match feed (competition 72, Solana devnet)",
  "generatedAt": "2026-07-19T06:16:03.088Z"
}
